NeuroAnalysisTools/CamstimTools.py
NeuroAnalysisTools/DatabaseTools.py
NeuroAnalysisTools/DeepLabCutTools.py
NeuroAnalysisTools/DisplayLogTools.py
NeuroAnalysisTools/HighLevel.py
NeuroAnalysisTools/ImageChunkTools.py
NeuroAnalysisTools/MotionCorrection.py
NeuroAnalysisTools/MotionCorrection_old.py
NeuroAnalysisTools/NwbTools.py
NeuroAnalysisTools/PreprocessPipeline.py
NeuroAnalysisTools/RetinotopicMapping.py
NeuroAnalysisTools/SingleCellAnalysis.py
NeuroAnalysisTools/Suite2pTools.py
NeuroAnalysisTools/SwcTools.py
NeuroAnalysisTools/VasculatureMapMatching.py
NeuroAnalysisTools/__init__.py
NeuroAnalysisTools/core/DataAnalysis.py
NeuroAnalysisTools/core/FileTools.py
NeuroAnalysisTools/core/ImageAnalysis.py
NeuroAnalysisTools/core/PlottingTools.py
NeuroAnalysisTools/core/TimingAnalysis.py
NeuroAnalysisTools/core/__init__.py
NeuroAnalysisTools/external/__init__.py
NeuroAnalysisTools/external/r_neuropil.py
NeuroAnalysisTools/external/nwb/__init__.py
NeuroAnalysisTools/external/nwb/license.txt
NeuroAnalysisTools/external/nwb/nwb.py
NeuroAnalysisTools/external/nwb/nwbco.py
NeuroAnalysisTools/external/nwb/nwbep.py
NeuroAnalysisTools/external/nwb/nwbmo.py
NeuroAnalysisTools/external/nwb/nwbts.py
NeuroAnalysisTools/external/nwb/spec_epoch.json
NeuroAnalysisTools/external/nwb/spec_file.json
NeuroAnalysisTools/external/nwb/spec_general.json
NeuroAnalysisTools/external/nwb/spec_iface.json
NeuroAnalysisTools/external/nwb/spec_mod.json
NeuroAnalysisTools/external/nwb/spec_ts.json
NeuroAnalysisTools/nwb/__init__.py
NeuroAnalysisTools/nwb/license.txt
NeuroAnalysisTools/nwb/nwb.py
NeuroAnalysisTools/nwb/nwbco.py
NeuroAnalysisTools/nwb/nwbep.py
NeuroAnalysisTools/nwb/nwbmo.py
NeuroAnalysisTools/nwb/nwbts.py
NeuroAnalysisTools/nwb/spec_epoch.json
NeuroAnalysisTools/nwb/spec_file.json
NeuroAnalysisTools/nwb/spec_general.json
NeuroAnalysisTools/nwb/spec_iface.json
NeuroAnalysisTools/nwb/spec_mod.json
NeuroAnalysisTools/nwb/spec_ts.json
NeuroAnalysisTools-3.0.1.dist-info/METADATA
NeuroAnalysisTools-3.0.1.dist-info/WHEEL
NeuroAnalysisTools-3.0.1.dist-info/top_level.txt
NeuroAnalysisTools-3.0.1.dist-info/RECORD
