Metadata-Version: 2.1
Name: NeuroAnalysisTools
Version: 3.0.1
Summary: Data analysis tools for systems neuroscience
Home-page: https://github.com/zhuangjun1981/NeuroAnalysisTools.git
Author: Jun Zhuang
Author-email: junz@alleninstitute.org
License: UNKNOWN
Platform: any
Classifier: Programming Language :: Python
Classifier: Development Status :: 4 - Beta
Classifier: Natural Language :: English
Classifier: Operating System :: OS Independent
Requires-Python: >3.0
Requires-Dist: seaborn
Requires-Dist: cython
Requires-Dist: scikit-learn
Requires-Dist: scikit-image
Requires-Dist: pillow
Requires-Dist: pytest
Requires-Dist: opencv-python
Requires-Dist: tifffile
Requires-Dist: h5py
Requires-Dist: pandas
Requires-Dist: matplotlib
Requires-Dist: scipy
Requires-Dist: numpy
